hydra_zen/__init__.py
hydra_zen/_compatibility.py
hydra_zen/_hydra_overloads.py
hydra_zen/_launch.py
hydra_zen/_py314_compat.py
hydra_zen/_version.py
hydra_zen/errors.py
hydra_zen/funcs.py
hydra_zen/py.typed
hydra_zen/_utils/__init__.py
hydra_zen/_utils/coerce.py
hydra_zen/structured_configs/__init__.py
hydra_zen/structured_configs/_globals.py
hydra_zen/structured_configs/_implementations.py
hydra_zen/structured_configs/_just.py
hydra_zen/structured_configs/_make_config.py
hydra_zen/structured_configs/_make_custom_builds.py
hydra_zen/structured_configs/_type_guards.py
hydra_zen/structured_configs/_utils.py
hydra_zen/third_party/__init__.py
hydra_zen/third_party/beartype.py
hydra_zen/third_party/pydantic.py
hydra_zen/typing/__init__.py
hydra_zen/typing/_builds_overloads.py
hydra_zen/typing/_implementations.py
hydra_zen/wrapper/__init__.py
hydra_zen/wrapper/_implementations.py
hydra_zen-0.16.0.dist-info/licenses/LICENSE.txt
hydra_zen-0.16.0.dist-info/METADATA
hydra_zen-0.16.0.dist-info/WHEEL
hydra_zen-0.16.0.dist-info/top_level.txt
hydra_zen-0.16.0.dist-info/RECORD
