Metadata-Version: 2.4
Name: hydra_zen
Version: 0.16.0
Summary: Configurable, reproducible, and scalable workflows in Python, via Hydra
Author-email: Ryan Soklaski <rsoklaski@gmail.com>, Justin Goodwin <jgoodwin@ll.mit.edu>
Maintainer-email: Justin Goodwin <jgoodwin@ll.mit.edu>
License: MIT
Project-URL: Homepage, https://mit-ll-responsible-ai.github.io/hydra-zen/
Project-URL: Bug Reports, https://github.com/mit-ll-responsible-ai/hydra-zen/issues
Project-URL: Source, https://github.com/mit-ll-responsible-ai/hydra-zen
Keywords: machine learning,research,configuration,scalable,reproducible,yaml,Hydra,dataclass
Classifier: Development Status :: 4 - Beta
Classifier: License :: OSI Approved :: MIT License
Classifier: Operating System :: OS Independent
Classifier: Intended Audience :: Science/Research
Classifier: Programming Language :: Python :: 3.9
Classifier: Programming Language :: Python :: 3.10
Classifier: Programming Language :: Python :: 3.11
Classifier: Programming Language :: Python :: 3.12
Classifier: Programming Language :: Python :: 3.13
Classifier: Programming Language :: Python :: 3.14
Classifier: Topic :: Scientific/Engineering
Classifier: Programming Language :: Python :: 3 :: Only
Requires-Python: >=3.9
License-File: LICENSE.txt
Requires-Dist: hydra-core>=1.2.0
Requires-Dist: omegaconf>=2.2.3
Requires-Dist: typing-extensions!=4.6.0,>=4.1.0
Provides-Extra: test
Requires-Dist: pytest>=3.9; extra == "test"
Requires-Dist: hypothesis>=6.28.0; extra == "test"
Requires-Dist: pytest-trio>=0.8.0; extra == "test"
Provides-Extra: pydantic
Requires-Dist: pydantic<2.0.0,>=1.10.14; extra == "pydantic"
Provides-Extra: beartype
Requires-Dist: beartype>=0.8.0; extra == "beartype"
Dynamic: license-file
